gitup/__init__.py
gitup/__main__.py
gitup/cli.py
gitup/config.py
gitup/migrate.py
gitup/update.py
gitup/test/__init__.py
gitup/test/test_bookmarks.py
gitup/test/test_cli.py
gitup-0.5.2.dist-info/METADATA
gitup-0.5.2.dist-info/WHEEL
gitup-0.5.2.dist-info/entry_points.txt
gitup-0.5.2.dist-info/licenses/LICENSE
gitup-0.5.2.dist-info/RECORD
