Metadata-Version: 2.4
Name: gitup
Version: 0.5.2
Summary: Easily update multiple git repositories at once
Project-URL: Repository, https://github.com/earwig/git-repo-updater
Project-URL: Issues, https://github.com/earwig/git-repo-updater/issues
Project-URL: Changelog, https://github.com/earwig/git-repo-updater/blob/main/CHANGELOG
Author-email: Ben Kurtovic <ben@benkurtovic.com>
License-Expression: MIT
License-File: LICENSE
Keywords: git,pull,repository,update
Classifier: Development Status :: 5 - Production/Stable
Classifier: Environment :: Console
Classifier: Intended Audience :: Developers
Classifier: License :: OSI Approved :: MIT License
Classifier: Natural Language :: English
Classifier: Operating System :: MacOS :: MacOS X
Classifier: Operating System :: Microsoft :: Windows
Classifier: Operating System :: POSIX
Classifier: Programming Language :: Python
Classifier: Programming Language :: Python :: 3
Classifier: Programming Language :: Python :: 3.8
Classifier: Programming Language :: Python :: 3.9
Classifier: Programming Language :: Python :: 3.10
Classifier: Programming Language :: Python :: 3.11
Classifier: Programming Language :: Python :: 3.12
Classifier: Programming Language :: Python :: 3.13
Classifier: Topic :: Software Development :: Version Control :: Git
Requires-Python: >=3.8
Requires-Dist: colorama>=0.4.6
Requires-Dist: gitpython>=3.1.1
